Metadata-Version: 2.1
Name: example-pkg-cloutpy
Version: 0.0.1
Summary: Package to check if TikTok Username is available
Home-page: https://api.cloutflare.tech
Author: clout
Author-email: admin@cloutflare.tech
License: UNKNOWN
Platform: UNKNOWN
Classifier: Programming Language :: Python :: 3
Classifier: License :: OSI Approved :: MIT License
Classifier: Operating System :: OS Independent
Requires-Python: >=3.6
